credisur/__init__.py
credisur/__main__.py
credisur/version.py
credisur/bankparser/__init__.py
credisur/bankparser/bankparser.py
credisur/config/__init__.py
credisur/config/advance_payments_columns.py
credisur/config/bank_debits_columns.py
credisur/config/columns_configuration.py
credisur/config/debtors_columns.py
credisur/config/last_payment_columns.py
credisur/config/no_payment_due_columns.py
credisur/datastructures/__init__.py
credisur/datastructures/hashoflists.py
credisur/dateintelligence/__init__.py
credisur/dateintelligence/calendaroperations.py
credisur/debitsgenerator/__init__.py
credisur/debitsgenerator/debitgenerator.py
credisur/debitsgenerator/errornotification.py
credisur/debitsgenerator/filenamebuilder.py
credisur/debitsgenerator/notifyerrors.py
credisur/debitsgenerator/readdebitsexcel.py
credisur/debitsgenerator/models/__init__.py
credisur/debitsgenerator/parsers/__init__.py
credisur/debitsgenerator/parsers/lastlinecalculator.py
credisur/debitsgenerator/parsers/parsedebitsheaders.py
credisur/debitsgenerator/parsers/parsedebitslines.py
credisur/debitsgenerator/validators/__init__.py
credisur/debitsgenerator/validators/errorsiterator.py
credisur/debitsgenerator/validators/validatefile.py
credisur/debitsgenerator/validators/validateheaders.py
credisur/debitsgenerator/validators/validatelines.py
credisur/debitsgenerator/writers/__init__.py
credisur/debitsgenerator/writers/streamers.py
credisur/exceladapter/__init__.py
credisur/exceladapter/excelbasiccomposer.py
credisur/exceladapter/excelreader.py
credisur/exceladapter/excelupgrader.py
credisur/exceladapter/excelwriter.py
credisur/excelbuilder/__init__.py
credisur/excelbuilder/basicbuilder.py
credisur/extractors/__init__.py
credisur/extractors/account_receivable_extractor.py
credisur/extractors/account_receivable_extractor_results.py
credisur/extractors/bill_extractor_results.py
credisur/extractors/bill_row_extractor.py
credisur/extractors/collection_row_extractor.py
credisuretl-0.1.48.dist-info/METADATA
credisuretl-0.1.48.dist-info/WHEEL
credisuretl-0.1.48.dist-info/entry_points.txt
credisuretl-0.1.48.dist-info/top_level.txt
credisuretl-0.1.48.dist-info/RECORD
