Metadata-Version: 2.1
Name: credisuretl
Version: 0.1.48
Summary: ETL for Felsim
Home-page: http://github.com/fedegos/credisuretl
Author: Federico Gosman
Author-email: federico@equipogsm.com
License: MIT
Platform: UNKNOWN
Requires-Dist: openpyxl (==2.4.7)
Requires-Dist: xlrd
Requires-Dist: python-dateutil (==2.8.0)
